setup.cfg
setup.py
vibra/__init__.py
vibra/crypto.py
vibra.egg-info/PKG-INFO
vibra.egg-info/SOURCES.txt
vibra.egg-info/dependency_links.txt
vibra.egg-info/requires.txt
vibra.egg-info/top_level.txt
vibra/firefly/__init__.py
vibra/firefly/built_in.py
vibra/firefly/data.py
vibra/firefly/file.py
vibra/firefly/data/__init__.py
vibra/firefly/data/data.py
vibra/firefly/data/dataset.py